holoviews/__init__.py
holoviews/__version.py
holoviews/_version.py
holoviews/annotators.py
holoviews/pyodide.py
holoviews/selection.py
holoviews/streams.py
holoviews/core/__init__.py
holoviews/core/accessors.py
holoviews/core/boundingregion.py
holoviews/core/decollate.py
holoviews/core/dimension.py
holoviews/core/element.py
holoviews/core/io.py
holoviews/core/layout.py
holoviews/core/ndmapping.py
holoviews/core/operation.py
holoviews/core/options.py
holoviews/core/overlay.py
holoviews/core/pprint.py
holoviews/core/sheetcoords.py
holoviews/core/spaces.py
holoviews/core/traversal.py
holoviews/core/tree.py
holoviews/core/data/__init__.py
holoviews/core/data/array.py
holoviews/core/data/cudf.py
holoviews/core/data/dask.py
holoviews/core/data/dictionary.py
holoviews/core/data/grid.py
holoviews/core/data/ibis.py
holoviews/core/data/image.py
holoviews/core/data/interface.py
holoviews/core/data/multipath.py
holoviews/core/data/narwhals.py
holoviews/core/data/pandas.py
holoviews/core/data/spatialpandas.py
holoviews/core/data/spatialpandas_dask.py
holoviews/core/data/util.py
holoviews/core/data/xarray.py
holoviews/core/util/__init__.py
holoviews/core/util/dependencies.py
holoviews/core/util/types.py
holoviews/element/__init__.py
holoviews/element/annotation.py
holoviews/element/chart.py
holoviews/element/chart3d.py
holoviews/element/comparison.py
holoviews/element/geom.py
holoviews/element/graphs.py
holoviews/element/path.py
holoviews/element/raster.py
holoviews/element/sankey.py
holoviews/element/selection.py
holoviews/element/stats.py
holoviews/element/tabular.py
holoviews/element/tiles.py
holoviews/element/util.py
holoviews/examples/README.md
holoviews/examples/conftest.py
holoviews/examples/assets/README.rst
holoviews/examples/assets/aggregator.png
holoviews/examples/assets/data_range.png
holoviews/examples/assets/diseases.csv.gz
holoviews/examples/assets/emoji_embeddings.csv
holoviews/examples/assets/energy.csv
holoviews/examples/assets/fb_edges.csv
holoviews-1.22.0.dist-info/METADATA
holoviews-1.22.0.dist-info/WHEEL
holoviews-1.22.0.dist-info/entry_points.txt
holoviews-1.22.0.dist-info/licenses/LICENSE.txt
holoviews-1.22.0.dist-info/RECORD
