Metadata-Version: 2.4
Name: holoviews
Version: 1.22.0
Summary: A high-level plotting API for the PyData ecosystem built on HoloViews.
Project-URL: Issue Tracker, https://github.com/holoviz/holoviews/issues?q=sort%3Aupdated-desc+is%3Aissue+is%3Aopen
Project-URL: Blog, https://blog.holoviz.org/
Project-URL: Changelog, https://github.com/holoviz/holoviews/blob/main/doc/releases.md
Project-URL: Discord, https://discord.gg/AXRHnJU6sP
Project-URL: Discourse, https://discourse.holoviz.org
Project-URL: Discussions, https://github.com/holoviz/holoviews/discussions
Project-URL: Documentation, https://holoviews.org/
Project-URL: Funding, https://opencollective.com/holoviz
Project-URL: HoloViz, https://holoviz.org/
Project-URL: Homepage, https://holoviews.org
Project-URL: Repository, https://github.com/holoviz/holoviews
Author-email: Jean-Luc Stevens <developers@holoviz.org>, Philipp Rudiger <developers@holoviz.org>
Maintainer-email: HoloViz developers <developers@holoviz.org>
License-Expression: BSD-3-Clause
License-File: LICENSE.txt
Classifier: Development Status :: 5 - Production/Stable
Classifier: Framework :: Matplotlib
Classifier: Intended Audience :: Developers
Classifier: Intended Audience :: Science/Research
Classifier: Natural Language :: English
Classifier: Operating System :: OS Independent
Classifier: Programming Language :: Python :: 3.10
Classifier: Programming Language :: Python :: 3.11
Classifier: Programming Language :: Python :: 3.12
Classifier: Programming Language :: Python :: 3.13
Classifier: Programming Language :: Python :: 3.14
Classifier: Topic :: Scientific/Engineering
Classifier: Topic :: Software Development :: Libraries
Requires-Python: >=3.10
Requires-Dist: bokeh>=3.1
Requires-Dist: colorcet
Requires-Dist: narwhals>=2
Requires-Dist: numpy>=1.21
Requires-Dist: packaging
Requires-Dist: pandas>=1.3
Requires-Dist: panel>=1.0
Requires-Dist: param<3.0,>=2.0
Requires-Dist: python-dateutil>=2.8.2
Requires-Dist: pyviz-comms>=2.1
Provides-Extra: recommended
Requires-Dist: matplotlib>=3; extra == 'recommended'
Requires-Dist: plotly>=4.0; extra == 'recommended'
